{
  "acumulado": true,
  "dataApuracao": "23/06/2018",
  "dataProximoConcurso": "26/06/2018",
  "dezenasSorteadasOrdemSorteio": [
    "26",
    "13",
    "16",
    "08",
    "11",
    "29",
    "28"
  ],
  "exibirDetalhamentoPorCidade": true,
  "id": null,
  "indicadorConcursoEspecial": 1,
  "listaDezenas": [
    "08",
    "11",
    "13",
    "16",
    "26",
    "28",
    "29"
  ],
  "listaDezenasSegundoSorteio": null,
  "listaMunicipioUFGanhadores": [],
  "listaRateioPremio": [
    {
      "descricaoFaixa": "7 acertos",
      "faixa": 1,
      "numeroDeGanhadores": 0,
      "valorPremio": 0.0
    },
    {
      "descricaoFaixa": "6 acertos",
      "faixa": 2,
      "numeroDeGanhadores": 131,
      "valorPremio": 2380.4
    },
    {
      "descricaoFaixa": "5 acertos",
      "faixa": 3,
      "numeroDeGanhadores": 5552,
      "valorPremio": 20.0
    },
    {
      "descricaoFaixa": "4 acertos",
      "faixa": 4,
      "numeroDeGanhadores": 70164,
      "valorPremio": 4.0
    },
    {
      "descricaoFaixa": "Mês da Sorte",
      "faixa": 5,
      "numeroDeGanhadores": 200142,
      "valorPremio": 2.0
    }
  ],
  "listaResultadoEquipeEsportiva": null,
  "localSorteio": "Caminhão da Sorte",
  "nomeMunicipioUFSorteio": "CAMPINA GRANDE, PB",
  "nomeTimeCoracaoMesSorte": "11",
  "numero": 15,
  "numeroConcursoAnterior": 14,
  "numeroConcursoFinal_0_5": 0,
  "numeroConcursoProximo": 16,
  "numeroJogo": 11,
  "observacao": "",
  "premiacaoContingencia": null,
  "tipoJogo": "DIA_DE_SORTE",
  "tipoPublicacao": 3,
  "ultimoConcurso": true,
  "valorArrecadado": 5252442.0,
  "valorAcumuladoConcurso_0_5": 0.0,
  "valorAcumuladoConcursoEspecial": 0.0,
  "valorAcumuladoProximoConcurso": 2425086.72,
  "valorEstimadoProximoConcurso": 3000000.0,
  "valorSaldoReservaGarantidora": 0.0,
  "valorTotalPremioFaixaUm": 0.0
}