{
  "acumulado": true,
  "dataApuracao": "22/01/2008",
  "dataProximoConcurso": "24/01/2008",
  "dezenasSorteadasOrdemSorteio": [
    "38",
    "08",
    "67",
    "60",
    "50"
  ],
  "exibirDetalhamentoPorCidade": true,
  "id": null,
  "indicadorConcursoEspecial": 1,
  "listaDezenas": [
    "08",
    "38",
    "50",
    "60",
    "67"
  ],
  "listaDezenasSegundoSorteio": null,
  "listaMunicipioUFGanhadores": [],
  "listaRateioPremio": [
    {
      "descricaoFaixa": "5 acertos",
      "faixa": 1,
      "numeroDeGanhadores": 0,
      "valorPremio": 0.0
    },
    {
      "descricaoFaixa": "4 acertos",
      "faixa": 2,
      "numeroDeGanhadores": 134,
      "valorPremio": 3178.57
    },
    {
      "descricaoFaixa": "3 acertos",
      "faixa": 3,
      "numeroDeGanhadores": 8480,
      "valorPremio": 66.97
    }
  ],
  "listaResultadoEquipeEsportiva": null,
  "localSorteio": "Caminhão da Sorte",
  "nomeMunicipioUFSorteio": "SÃO JOÃO DA BARRA, RJ",
  "nomeTimeCoracaoMesSorte": "",
  "numero": 1854,
  "numeroConcursoAnterior": 1853,
  "numeroConcursoFinal_0_5": 1855,
  "numeroConcursoProximo": 1855,
  "numeroJogo": 3,
  "observacao": "",
  "premiacaoContingencia": null,
  "tipoJogo": "QUINA",
  "tipoPublicacao": 3,
  "ultimoConcurso": true,
  "valorArrecadado": 0.0,
  "valorAcumuladoConcurso_0_5": 0.0,
  "valorAcumuladoConcursoEspecial": 0.0,
  "valorAcumuladoProximoConcurso": 781264.07,
  "valorEstimadoProximoConcurso": 1300000.0,
  "valorSaldoReservaGarantidora": 0.0,
  "valorTotalPremioFaixaUm": 0.0
}