{
  "acumulado": true,
  "dataApuracao": "05/09/2014",
  "dataProximoConcurso": "06/09/2014",
  "dezenasSorteadasOrdemSorteio": [
    "44",
    "18",
    "06",
    "16",
    "41"
  ],
  "exibirDetalhamentoPorCidade": true,
  "id": null,
  "indicadorConcursoEspecial": 1,
  "listaDezenas": [
    "06",
    "16",
    "18",
    "41",
    "44"
  ],
  "listaDezenasSegundoSorteio": null,
  "listaMunicipioUFGanhadores": [],
  "listaRateioPremio": [
    {
      "descricaoFaixa": "5 acertos",
      "faixa": 1,
      "numeroDeGanhadores": 0,
      "valorPremio": 0.0
    },
    {
      "descricaoFaixa": "4 acertos",
      "faixa": 2,
      "numeroDeGanhadores": 83,
      "valorPremio": 5945.41
    },
    {
      "descricaoFaixa": "3 acertos",
      "faixa": 3,
      "numeroDeGanhadores": 6215,
      "valorPremio": 113.42
    }
  ],
  "listaResultadoEquipeEsportiva": null,
  "localSorteio": "Estúdio de TV",
  "nomeMunicipioUFSorteio": "OSASCO, SP",
  "nomeTimeCoracaoMesSorte": "",
  "numero": 3580,
  "numeroConcursoAnterior": 3579,
  "numeroConcursoFinal_0_5": 3585,
  "numeroConcursoProximo": 3581,
  "numeroJogo": 3,
  "observacao": "",
  "premiacaoContingencia": null,
  "tipoJogo": "QUINA",
  "tipoPublicacao": 3,
  "ultimoConcurso": true,
  "valorArrecadado": 6405906.0,
  "valorAcumuladoConcurso_0_5": 0.0,
  "valorAcumuladoConcursoEspecial": 21087360.03,
  "valorAcumuladoProximoConcurso": 1247119.62,
  "valorEstimadoProximoConcurso": 2000000.0,
  "valorSaldoReservaGarantidora": 0.0,
  "valorTotalPremioFaixaUm": 0.0
}