{
  "acumulado": true,
  "dataApuracao": "15/01/2015",
  "dataProximoConcurso": "16/01/2015",
  "dezenasSorteadasOrdemSorteio": [
    "63",
    "28",
    "64",
    "67",
    "35"
  ],
  "exibirDetalhamentoPorCidade": true,
  "id": null,
  "indicadorConcursoEspecial": 1,
  "listaDezenas": [
    "28",
    "35",
    "63",
    "64",
    "67"
  ],
  "listaDezenasSegundoSorteio": null,
  "listaMunicipioUFGanhadores": [],
  "listaRateioPremio": [
    {
      "descricaoFaixa": "5 acertos",
      "faixa": 1,
      "numeroDeGanhadores": 0,
      "valorPremio": 0.0
    },
    {
      "descricaoFaixa": "4 acertos",
      "faixa": 2,
      "numeroDeGanhadores": 105,
      "valorPremio": 5210.77
    },
    {
      "descricaoFaixa": "3 acertos",
      "faixa": 3,
      "numeroDeGanhadores": 5874,
      "valorPremio": 133.06
    },
    {
      "descricaoFaixa": "2 acertos",
      "faixa": 4,
      "numeroDeGanhadores": 0,
      "valorPremio": 0.0
    }
  ],
  "listaResultadoEquipeEsportiva": null,
  "localSorteio": "Estúdio de TV",
  "nomeMunicipioUFSorteio": "OSASCO, SP",
  "nomeTimeCoracaoMesSorte": "",
  "numero": 3690,
  "numeroConcursoAnterior": 3689,
  "numeroConcursoFinal_0_5": 3695,
  "numeroConcursoProximo": 3691,
  "numeroJogo": 3,
  "observacao": "",
  "premiacaoContingencia": null,
  "tipoJogo": "QUINA",
  "tipoPublicacao": 3,
  "ultimoConcurso": true,
  "valorArrecadado": 7102508.0,
  "valorAcumuladoConcurso_0_5": 0.0,
  "valorAcumuladoConcursoEspecial": 55344834.82,
  "valorAcumuladoProximoConcurso": 2045771.12,
  "valorEstimadoProximoConcurso": 2800000.0,
  "valorSaldoReservaGarantidora": 0.0,
  "valorTotalPremioFaixaUm": 0.0
}