{
  "acumulado": false,
  "dataApuracao": "30/08/2017",
  "dataProximoConcurso": "31/08/2017",
  "dezenasSorteadasOrdemSorteio": [
    "12",
    "60",
    "78",
    "71",
    "63"
  ],
  "exibirDetalhamentoPorCidade": true,
  "id": null,
  "indicadorConcursoEspecial": 1,
  "listaDezenas": [
    "12",
    "60",
    "63",
    "71",
    "78"
  ],
  "listaDezenasSegundoSorteio": null,
  "listaMunicipioUFGanhadores": [
    {
      "ganhadores": 1,
      "municipio": "ITAPORA",
      "nomeFatansiaUL": "",
      "posicao": 1,
      "serie": "",
      "uf": "MS"
    }
  ],
  "listaRateioPremio": [
    {
      "descricaoFaixa": "5 acertos",
      "faixa": 1,
      "numeroDeGanhadores": 1,
      "valorPremio": 639542.5
    },
    {
      "descricaoFaixa": "4 acertos",
      "faixa": 2,
      "numeroDeGanhadores": 34,
      "valorPremio": 10211.18
    },
    {
      "descricaoFaixa": "3 acertos",
      "faixa": 3,
      "numeroDeGanhadores": 2730,
      "valorPremio": 191.23
    },
    {
      "descricaoFaixa": "2 acertos",
      "faixa": 4,
      "numeroDeGanhadores": 84311,
      "valorPremio": 3.4
    }
  ],
  "listaResultadoEquipeEsportiva": null,
  "localSorteio": "ESPAÇO LOTERIAS CAIXA",
  "nomeMunicipioUFSorteio": "SÃO PAULO, SP",
  "nomeTimeCoracaoMesSorte": "",
  "numero": 4469,
  "numeroConcursoAnterior": 4468,
  "numeroConcursoFinal_0_5": 4475,
  "numeroConcursoProximo": 4470,
  "numeroJogo": 3,
  "observacao": "",
  "premiacaoContingencia": null,
  "tipoJogo": "QUINA",
  "tipoPublicacao": 3,
  "ultimoConcurso": true,
  "valorArrecadado": 6021732.0,
  "valorAcumuladoConcurso_0_5": 0.0,
  "valorAcumuladoConcursoEspecial": 21544453.71,
  "valorAcumuladoProximoConcurso": 0.0,
  "valorEstimadoProximoConcurso": 600000.0,
  "valorSaldoReservaGarantidora": 0.0,
  "valorTotalPremioFaixaUm": 0.0
}