{
  "acumulado": false,
  "dataApuracao": "21/12/2017",
  "dataProximoConcurso": "22/12/2017",
  "dezenasSorteadasOrdemSorteio": [
    "10",
    "54",
    "19",
    "36",
    "15"
  ],
  "exibirDetalhamentoPorCidade": true,
  "id": null,
  "indicadorConcursoEspecial": 1,
  "listaDezenas": [
    "10",
    "15",
    "19",
    "36",
    "54"
  ],
  "listaDezenasSegundoSorteio": null,
  "listaMunicipioUFGanhadores": [
    {
      "ganhadores": 1,
      "municipio": "SALVADOR",
      "nomeFatansiaUL": "",
      "posicao": 1,
      "serie": "",
      "uf": "BA"
    }
  ],
  "listaRateioPremio": [
    {
      "descricaoFaixa": "5 acertos",
      "faixa": 1,
      "numeroDeGanhadores": 1,
      "valorPremio": 2087097.14
    },
    {
      "descricaoFaixa": "4 acertos",
      "faixa": 2,
      "numeroDeGanhadores": 112,
      "valorPremio": 3689.59
    },
    {
      "descricaoFaixa": "3 acertos",
      "faixa": 3,
      "numeroDeGanhadores": 8442,
      "valorPremio": 73.6
    },
    {
      "descricaoFaixa": "2 acertos",
      "faixa": 4,
      "numeroDeGanhadores": 177642,
      "valorPremio": 1.92
    }
  ],
  "listaResultadoEquipeEsportiva": null,
  "localSorteio": "Caminhão da Sorte",
  "nomeMunicipioUFSorteio": "PORTO UNIÃO, SC",
  "nomeTimeCoracaoMesSorte": "",
  "numero": 4562,
  "numeroConcursoAnterior": 4561,
  "numeroConcursoFinal_0_5": 4565,
  "numeroConcursoProximo": 4563,
  "numeroJogo": 3,
  "observacao": "",
  "premiacaoContingencia": null,
  "tipoJogo": "QUINA",
  "tipoPublicacao": 3,
  "ultimoConcurso": true,
  "valorArrecadado": 7167412.5,
  "valorAcumuladoConcurso_0_5": 0.0,
  "valorAcumuladoConcursoEspecial": 54056687.63,
  "valorAcumuladoProximoConcurso": 0.0,
  "valorEstimadoProximoConcurso": 600000.0,
  "valorSaldoReservaGarantidora": 0.0,
  "valorTotalPremioFaixaUm": 0.0
}