{
  "acumulado": false,
  "dataApuracao": "14/02/2002",
  "dataProximoConcurso": "02/02/2002",
  "dezenasSorteadasOrdemSorteio": [
    "44",
    "73",
    "75",
    "76",
    "22"
  ],
  "exibirDetalhamentoPorCidade": true,
  "id": null,
  "indicadorConcursoEspecial": 1,
  "listaDezenas": [
    "22",
    "44",
    "73",
    "75",
    "76"
  ],
  "listaDezenasSegundoSorteio": null,
  "listaMunicipioUFGanhadores": [
    {
      "ganhadores": 1,
      "municipio": "",
      "nomeFatansiaUL": "",
      "posicao": 1,
      "serie": "",
      "uf": "GO"
    }
  ],
  "listaRateioPremio": [
    {
      "descricaoFaixa": "5 acertos",
      "faixa": 1,
      "numeroDeGanhadores": 1,
      "valorPremio": 273466.87
    },
    {
      "descricaoFaixa": "4 acertos",
      "faixa": 2,
      "numeroDeGanhadores": 265,
      "valorPremio": 1031.95
    },
    {
      "descricaoFaixa": "3 acertos",
      "faixa": 3,
      "numeroDeGanhadores": 10561,
      "valorPremio": 34.4
    }
  ],
  "listaResultadoEquipeEsportiva": null,
  "localSorteio": "Caminhão da Sorte",
  "nomeMunicipioUFSorteio": "Vargem Grande do Sul, SP",
  "nomeTimeCoracaoMesSorte": "",
  "numero": 955,
  "numeroConcursoAnterior": 954,
  "numeroConcursoFinal_0_5": 965,
  "numeroConcursoProximo": 956,
  "numeroJogo": 3,
  "observacao": "Estimativa de prêmio (QUINA) próximo concurso: R$330.000,00.",
  "premiacaoContingencia": null,
  "tipoJogo": "QUINA",
  "tipoPublicacao": 3,
  "ultimoConcurso": true,
  "valorArrecadado": 0.0,
  "valorAcumuladoConcurso_0_5": 0.0,
  "valorAcumuladoConcursoEspecial": 0.0,
  "valorAcumuladoProximoConcurso": 0.0,
  "valorEstimadoProximoConcurso": 0.0,
  "valorSaldoReservaGarantidora": 0.0,
  "valorTotalPremioFaixaUm": 0.0
}