{
  "acumulado": true,
  "dataApuracao": "05/12/1973",
  "dataProximoConcurso": "",
  "dezenasSorteadasOrdemSorteio": [
    "042964",
    "024478",
    "022211",
    "018274",
    "002218"
  ],
  "exibirDetalhamentoPorCidade": true,
  "id": null,
  "indicadorConcursoEspecial": 1,
  "listaDezenas": [
    "042964",
    "024478",
    "022211",
    "018274",
    "002218"
  ],
  "listaDezenasSegundoSorteio": null,
  "listaMunicipioUFGanhadores": [],
  "listaRateioPremio": [
    {
      "descricaoFaixa": "1 acertos",
      "faixa": 1,
      "numeroDeGanhadores": 0,
      "valorPremio": 200000.0
    },
    {
      "descricaoFaixa": "2 acertos",
      "faixa": 2,
      "numeroDeGanhadores": 0,
      "valorPremio": 8000.0
    },
    {
      "descricaoFaixa": "3 acertos",
      "faixa": 3,
      "numeroDeGanhadores": 0,
      "valorPremio": 5000.0
    },
    {
      "descricaoFaixa": "4 acertos",
      "faixa": 4,
      "numeroDeGanhadores": 0,
      "valorPremio": 4000.0
    },
    {
      "descricaoFaixa": "5 acertos",
      "faixa": 5,
      "numeroDeGanhadores": 0,
      "valorPremio": 2000.0
    }
  ],
  "listaResultadoEquipeEsportiva": null,
  "localSorteio": "",
  "nomeMunicipioUFSorteio": "",
  "nomeTimeCoracaoMesSorte": "",
  "numero": 1089,
  "numeroConcursoAnterior": 1088,
  "numeroConcursoFinal_0_5": 0,
  "numeroConcursoProximo": 1090,
  "numeroJogo": 10,
  "observacao": "",
  "premiacaoContingencia": null,
  "tipoJogo": "LOTERIA_FEDERAL",
  "tipoPublicacao": 3,
  "ultimoConcurso": true,
  "valorArrecadado": 0.0,
  "valorAcumuladoConcurso_0_5": 0.0,
  "valorAcumuladoConcursoEspecial": 0.0,
  "valorAcumuladoProximoConcurso": 0.0,
  "valorEstimadoProximoConcurso": 0.0,
  "valorSaldoReservaGarantidora": 0.0,
  "valorTotalPremioFaixaUm": 0.0
}