{
  "acumulado": true,
  "dataApuracao": "13/03/2012",
  "dataProximoConcurso": "16/03/2012",
  "dezenasSorteadasOrdemSorteio": [
    "33",
    "22",
    "20",
    "04",
    "09",
    "42",
    "05",
    "15",
    "07",
    "22",
    "01",
    "13"
  ],
  "exibirDetalhamentoPorCidade": true,
  "id": null,
  "indicadorConcursoEspecial": 1,
  "listaDezenas": [
    "04",
    "09",
    "20",
    "22",
    "33",
    "42"
  ],
  "listaDezenasSegundoSorteio": [
    "01",
    "05",
    "07",
    "13",
    "15",
    "22"
  ],
  "listaMunicipioUFGanhadores": [],
  "listaRateioPremio": [
    {
      "descricaoFaixa": "6 acertos",
      "faixa": 1,
      "numeroDeGanhadores": 0,
      "valorPremio": 0.0
    },
    {
      "descricaoFaixa": "5 acertos",
      "faixa": 2,
      "numeroDeGanhadores": 41,
      "valorPremio": 3921.86
    },
    {
      "descricaoFaixa": "4 acertos",
      "faixa": 3,
      "numeroDeGanhadores": 3005,
      "valorPremio": 50.96
    },
    {
      "descricaoFaixa": "6 acertos",
      "faixa": 5,
      "numeroDeGanhadores": 0,
      "valorPremio": 0.0
    },
    {
      "descricaoFaixa": "5 acertos",
      "faixa": 6,
      "numeroDeGanhadores": 99,
      "valorPremio": 1624.21
    },
    {
      "descricaoFaixa": "4 acertos",
      "faixa": 7,
      "numeroDeGanhadores": 4426,
      "valorPremio": 34.59
    }
  ],
  "listaResultadoEquipeEsportiva": null,
  "localSorteio": "Caminhão da Sorte",
  "nomeMunicipioUFSorteio": "ITUPORANGA, SC",
  "nomeTimeCoracaoMesSorte": "",
  "numero": 1054,
  "numeroConcursoAnterior": 1053,
  "numeroConcursoFinal_0_5": 0,
  "numeroConcursoProximo": 1055,
  "numeroJogo": 18,
  "observacao": "",
  "premiacaoContingencia": null,
  "tipoJogo": "DUPLA_SENA",
  "tipoPublicacao": 3,
  "ultimoConcurso": true,
  "valorArrecadado": 3478925.0,
  "valorAcumuladoConcurso_0_5": 0.0,
  "valorAcumuladoConcursoEspecial": 0.0,
  "valorAcumuladoProximoConcurso": 3478296.39,
  "valorEstimadoProximoConcurso": 3800000.0,
  "valorSaldoReservaGarantidora": 0.0,
  "valorTotalPremioFaixaUm": 0.0
}