{
  "acumulado": true,
  "dataApuracao": "07/05/2020",
  "dataProximoConcurso": "09/05/2020",
  "dezenasSorteadasOrdemSorteio": [
    "20",
    "06",
    "18",
    "45",
    "44",
    "36",
    "46",
    "43",
    "11",
    "37",
    "05",
    "19"
  ],
  "exibirDetalhamentoPorCidade": true,
  "id": null,
  "indicadorConcursoEspecial": 1,
  "listaDezenas": [
    "06",
    "18",
    "20",
    "36",
    "44",
    "45"
  ],
  "listaDezenasSegundoSorteio": [
    "05",
    "11",
    "19",
    "37",
    "43",
    "46"
  ],
  "listaMunicipioUFGanhadores": [],
  "listaRateioPremio": [
    {
      "descricaoFaixa": "6 acertos",
      "faixa": 1,
      "numeroDeGanhadores": 0,
      "valorPremio": 0.0
    },
    {
      "descricaoFaixa": "5 acertos",
      "faixa": 2,
      "numeroDeGanhadores": 10,
      "valorPremio": 3904.48
    },
    {
      "descricaoFaixa": "4 acertos",
      "faixa": 3,
      "numeroDeGanhadores": 425,
      "valorPremio": 104.99
    },
    {
      "descricaoFaixa": "3 acertos",
      "faixa": 4,
      "numeroDeGanhadores": 8459,
      "valorPremio": 2.63
    },
    {
      "descricaoFaixa": "6 acertos",
      "faixa": 5,
      "numeroDeGanhadores": 0,
      "valorPremio": 0.0
    },
    {
      "descricaoFaixa": "5 acertos",
      "faixa": 6,
      "numeroDeGanhadores": 16,
      "valorPremio": 2196.27
    },
    {
      "descricaoFaixa": "4 acertos",
      "faixa": 7,
      "numeroDeGanhadores": 595,
      "valorPremio": 74.99
    },
    {
      "descricaoFaixa": "3 acertos",
      "faixa": 8,
      "numeroDeGanhadores": 9412,
      "valorPremio": 2.37
    }
  ],
  "listaResultadoEquipeEsportiva": null,
  "localSorteio": "ESPAÇO LOTERIAS CAIXA",
  "nomeMunicipioUFSorteio": "SÃO PAULO, SP",
  "nomeTimeCoracaoMesSorte": "\u0000\u0000\u0000\u0000\u0000\u0000\u0000\u0000\u0000\u0000\u0000\u0000\u0000\u0000\u0000\u0000\u0000",
  "numero": 2075,
  "numeroConcursoAnterior": 2074,
  "numeroConcursoFinal_0_5": 0,
  "numeroConcursoProximo": 2076,
  "numeroJogo": 18,
  "observacao": "",
  "premiacaoContingencia": null,
  "tipoJogo": "DUPLA_SENA",
  "tipoPublicacao": 3,
  "ultimoConcurso": true,
  "valorArrecadado": 1286695.0,
  "valorAcumuladoConcurso_0_5": 0.0,
  "valorAcumuladoConcursoEspecial": 279917.44,
  "valorAcumuladoProximoConcurso": 717288.13,
  "valorEstimadoProximoConcurso": 800000.0,
  "valorSaldoReservaGarantidora": 0.0,
  "valorTotalPremioFaixaUm": 0.0
}