{
  "acumulado": true,
  "dataApuracao": "29/04/2024",
  "dataProximoConcurso": "03/05/2024",
  "dezenasSorteadasOrdemSorteio": [
    "35",
    "08",
    "20",
    "02",
    "37",
    "07",
    "46",
    "44",
    "02",
    "01",
    "50",
    "34"
  ],
  "exibirDetalhamentoPorCidade": true,
  "id": null,
  "indicadorConcursoEspecial": 1,
  "listaDezenas": [
    "02",
    "07",
    "08",
    "20",
    "35",
    "37"
  ],
  "listaDezenasSegundoSorteio": [
    "01",
    "02",
    "34",
    "44",
    "46",
    "50"
  ],
  "listaMunicipioUFGanhadores": [],
  "listaRateioPremio": [
    {
      "descricaoFaixa": "6 acertos",
      "faixa": 1,
      "numeroDeGanhadores": 0,
      "valorPremio": 0.0
    },
    {
      "descricaoFaixa": "5 acertos",
      "faixa": 2,
      "numeroDeGanhadores": 14,
      "valorPremio": 4024.51
    },
    {
      "descricaoFaixa": "4 acertos",
      "faixa": 3,
      "numeroDeGanhadores": 582,
      "valorPremio": 110.63
    },
    {
      "descricaoFaixa": "3 acertos",
      "faixa": 4,
      "numeroDeGanhadores": 11575,
      "valorPremio": 2.78
    },
    {
      "descricaoFaixa": "6 acertos",
      "faixa": 5,
      "numeroDeGanhadores": 0,
      "valorPremio": 0.0
    },
    {
      "descricaoFaixa": "5 acertos",
      "faixa": 6,
      "numeroDeGanhadores": 8,
      "valorPremio": 6338.6
    },
    {
      "descricaoFaixa": "4 acertos",
      "faixa": 7,
      "numeroDeGanhadores": 578,
      "valorPremio": 111.4
    },
    {
      "descricaoFaixa": "3 acertos",
      "faixa": 8,
      "numeroDeGanhadores": 11846,
      "valorPremio": 2.71
    }
  ],
  "listaResultadoEquipeEsportiva": null,
  "localSorteio": "ESPAÇO DA SORTE",
  "nomeMunicipioUFSorteio": "SÃO PAULO, SP",
  "nomeTimeCoracaoMesSorte": "\u0000\u0000\u0000\u0000\u0000\u0000\u0000\u0000\u0000\u0000\u0000\u0000\u0000\u0000\u0000\u0000\u0000",
  "numero": 2656,
  "numeroConcursoAnterior": 2655,
  "numeroConcursoFinal_0_5": 0,
  "numeroConcursoProximo": 2657,
  "numeroJogo": 18,
  "observacao": "",
  "premiacaoContingencia": null,
  "tipoJogo": "DUPLA_SENA",
  "tipoPublicacao": 3,
  "ultimoConcurso": true,
  "valorArrecadado": 1856750.0,
  "valorAcumuladoConcurso_0_5": 0.0,
  "valorAcumuladoConcursoEspecial": 877850.05,
  "valorAcumuladoProximoConcurso": 2264966.25,
  "valorEstimadoProximoConcurso": 2500000.0,
  "valorSaldoReservaGarantidora": 0.0,
  "valorTotalPremioFaixaUm": 0.0
}