{
  "acumulado": true,
  "dataApuracao": "12/05/2025",
  "dataProximoConcurso": "14/05/2025",
  "dezenasSorteadasOrdemSorteio": [
    "32",
    "41",
    "10",
    "08",
    "39",
    "50",
    "30",
    "04",
    "13",
    "09",
    "40",
    "31"
  ],
  "exibirDetalhamentoPorCidade": true,
  "id": null,
  "indicadorConcursoEspecial": 1,
  "listaDezenas": [
    "08",
    "10",
    "32",
    "39",
    "41",
    "50"
  ],
  "listaDezenasSegundoSorteio": [
    "04",
    "09",
    "13",
    "30",
    "31",
    "40"
  ],
  "listaMunicipioUFGanhadores": [],
  "listaRateioPremio": [
    {
      "descricaoFaixa": "6 acertos",
      "faixa": 1,
      "numeroDeGanhadores": 0,
      "valorPremio": 0.0
    },
    {
      "descricaoFaixa": "5 acertos",
      "faixa": 2,
      "numeroDeGanhadores": 20,
      "valorPremio": 2866.15
    },
    {
      "descricaoFaixa": "4 acertos",
      "faixa": 3,
      "numeroDeGanhadores": 591,
      "valorPremio": 110.84
    },
    {
      "descricaoFaixa": "3 acertos",
      "faixa": 4,
      "numeroDeGanhadores": 11435,
      "valorPremio": 2.86
    },
    {
      "descricaoFaixa": "6 acertos",
      "faixa": 5,
      "numeroDeGanhadores": 0,
      "valorPremio": 0.0
    },
    {
      "descricaoFaixa": "5 acertos",
      "faixa": 6,
      "numeroDeGanhadores": 9,
      "valorPremio": 5732.31
    },
    {
      "descricaoFaixa": "4 acertos",
      "faixa": 7,
      "numeroDeGanhadores": 654,
      "valorPremio": 100.17
    },
    {
      "descricaoFaixa": "3 acertos",
      "faixa": 8,
      "numeroDeGanhadores": 11963,
      "valorPremio": 2.73
    }
  ],
  "listaResultadoEquipeEsportiva": null,
  "localSorteio": "ESPAÇO DA SORTE",
  "nomeMunicipioUFSorteio": "SÃO PAULO, SP",
  "nomeTimeCoracaoMesSorte": "\u0000\u0000\u0000\u0000\u0000\u0000\u0000\u0000\u0000\u0000\u0000\u0000\u0000\u0000\u0000\u0000\u0000",
  "numero": 2806,
  "numeroConcursoAnterior": 2805,
  "numeroConcursoFinal_0_5": 0,
  "numeroConcursoProximo": 2807,
  "numeroJogo": 18,
  "observacao": "",
  "premiacaoContingencia": null,
  "tipoJogo": "DUPLA_SENA",
  "tipoPublicacao": 3,
  "ultimoConcurso": true,
  "valorArrecadado": 1870065.0,
  "valorAcumuladoConcurso_0_5": 0.0,
  "valorAcumuladoConcursoEspecial": 692183.14,
  "valorAcumuladoProximoConcurso": 1773718.54,
  "valorEstimadoProximoConcurso": 2000000.0,
  "valorSaldoReservaGarantidora": 0.0,
  "valorTotalPremioFaixaUm": 0.0
}