{
  "acumulado": true,
  "dataApuracao": "01/12/2009",
  "dataProximoConcurso": "04/12/2009",
  "dezenasSorteadasOrdemSorteio": [
    "45",
    "40",
    "43",
    "36",
    "50",
    "31",
    "12",
    "33",
    "13",
    "49",
    "05",
    "15"
  ],
  "exibirDetalhamentoPorCidade": true,
  "id": null,
  "indicadorConcursoEspecial": 1,
  "listaDezenas": [
    "31",
    "36",
    "40",
    "43",
    "45",
    "50"
  ],
  "listaDezenasSegundoSorteio": [
    "05",
    "12",
    "13",
    "15",
    "33",
    "49"
  ],
  "listaMunicipioUFGanhadores": [],
  "listaRateioPremio": [
    {
      "descricaoFaixa": "6 acertos",
      "faixa": 1,
      "numeroDeGanhadores": 0,
      "valorPremio": 0.0
    },
    {
      "descricaoFaixa": "6 acertos",
      "faixa": 5,
      "numeroDeGanhadores": 1,
      "valorPremio": 162098.02
    },
    {
      "descricaoFaixa": "5 acertos",
      "faixa": 6,
      "numeroDeGanhadores": 34,
      "valorPremio": 3178.4
    },
    {
      "descricaoFaixa": "4 acertos",
      "faixa": 7,
      "numeroDeGanhadores": 2074,
      "valorPremio": 74.43
    }
  ],
  "listaResultadoEquipeEsportiva": null,
  "localSorteio": "Caminhão da Sorte",
  "nomeMunicipioUFSorteio": "RIBEIRÃO PRETO, SP",
  "nomeTimeCoracaoMesSorte": "",
  "numero": 816,
  "numeroConcursoAnterior": 815,
  "numeroConcursoFinal_0_5": 0,
  "numeroConcursoProximo": 817,
  "numeroJogo": 18,
  "observacao": "O BILHETE CONTEMPLADO COM A SENA DO 2º SORTEIO FOI ADQUIRIDO EM SÃO PAULO/SP.",
  "premiacaoContingencia": null,
  "tipoJogo": "DUPLA_SENA",
  "tipoPublicacao": 3,
  "ultimoConcurso": true,
  "valorArrecadado": 1753545.0,
  "valorAcumuladoConcurso_0_5": 0.0,
  "valorAcumuladoConcursoEspecial": 0.0,
  "valorAcumuladoProximoConcurso": 2356231.76,
  "valorEstimadoProximoConcurso": 2500000.0,
  "valorSaldoReservaGarantidora": 0.0,
  "valorTotalPremioFaixaUm": 0.0
}