{
  "acumulado": true,
  "dataApuracao": "03/07/2013",
  "dataProximoConcurso": "06/07/2013",
  "dezenasSorteadasOrdemSorteio": [
    "51",
    "32",
    "22",
    "34",
    "65",
    "99",
    "64",
    "48",
    "20",
    "41",
    "26",
    "31",
    "76",
    "58",
    "86",
    "19",
    "83",
    "75",
    "52",
    "35"
  ],
  "exibirDetalhamentoPorCidade": true,
  "id": null,
  "indicadorConcursoEspecial": 1,
  "listaDezenas": [
    "19",
    "20",
    "22",
    "26",
    "31",
    "32",
    "34",
    "35",
    "41",
    "48",
    "51",
    "52",
    "58",
    "64",
    "65",
    "75",
    "76",
    "83",
    "86",
    "99"
  ],
  "listaDezenasSegundoSorteio": null,
  "listaMunicipioUFGanhadores": [],
  "listaRateioPremio": [
    {
      "descricaoFaixa": "20 acertos",
      "faixa": 1,
      "numeroDeGanhadores": 0,
      "valorPremio": 0.0
    },
    {
      "descricaoFaixa": "19 acertos",
      "faixa": 2,
      "numeroDeGanhadores": 2,
      "valorPremio": 130110.23
    },
    {
      "descricaoFaixa": "18 acertos",
      "faixa": 3,
      "numeroDeGanhadores": 102,
      "valorPremio": 2551.18
    },
    {
      "descricaoFaixa": "17 acertos",
      "faixa": 4,
      "numeroDeGanhadores": 923,
      "valorPremio": 176.2
    },
    {
      "descricaoFaixa": "16 acertos",
      "faixa": 5,
      "numeroDeGanhadores": 5771,
      "valorPremio": 28.18
    },
    {
      "descricaoFaixa": "15 acertos",
      "faixa": 6,
      "numeroDeGanhadores": 0,
      "valorPremio": 0.0
    }
  ],
  "listaResultadoEquipeEsportiva": null,
  "localSorteio": "Caminhão da Sorte",
  "nomeMunicipioUFSorteio": "MINEIROS, GO",
  "nomeTimeCoracaoMesSorte": "",
  "numero": 1362,
  "numeroConcursoAnterior": 1361,
  "numeroConcursoFinal_0_5": 0,
  "numeroConcursoProximo": 1363,
  "numeroJogo": 16,
  "observacao": "",
  "premiacaoContingencia": null,
  "tipoJogo": "LOTOMANIA",
  "tipoPublicacao": 3,
  "ultimoConcurso": true,
  "valorArrecadado": 5278152.0,
  "valorAcumuladoConcurso_0_5": 0.0,
  "valorAcumuladoConcursoEspecial": 7956664.52,
  "valorAcumuladoProximoConcurso": 2120171.72,
  "valorEstimadoProximoConcurso": 3000000.0,
  "valorSaldoReservaGarantidora": 0.0,
  "valorTotalPremioFaixaUm": 0.0
}