{
  "acumulado": false,
  "dataApuracao": "28/10/2016",
  "dataProximoConcurso": "01/11/2016",
  "dezenasSorteadasOrdemSorteio": [
    "23",
    "45",
    "59",
    "69",
    "57",
    "30",
    "07",
    "56",
    "27",
    "52",
    "70",
    "93",
    "21",
    "76",
    "43",
    "89",
    "05",
    "83",
    "61",
    "18"
  ],
  "exibirDetalhamentoPorCidade": true,
  "id": null,
  "indicadorConcursoEspecial": 1,
  "listaDezenas": [
    "05",
    "07",
    "18",
    "21",
    "23",
    "27",
    "30",
    "43",
    "45",
    "52",
    "56",
    "57",
    "59",
    "61",
    "69",
    "70",
    "76",
    "83",
    "89",
    "93"
  ],
  "listaDezenasSegundoSorteio": null,
  "listaMunicipioUFGanhadores": [
    {
      "ganhadores": 1,
      "municipio": "PARNAMIRIM",
      "nomeFatansiaUL": "",
      "posicao": 2,
      "serie": "",
      "uf": "RN"
    },
    {
      "ganhadores": 1,
      "municipio": "SUMARÉ",
      "nomeFatansiaUL": "",
      "posicao": 1,
      "serie": "",
      "uf": "SP"
    },
    {
      "ganhadores": 1,
      "municipio": "SUMARÉ",
      "nomeFatansiaUL": "",
      "posicao": 2,
      "serie": "",
      "uf": "SP"
    },
    {
      "ganhadores": 1,
      "municipio": "PALMAS",
      "nomeFatansiaUL": "",
      "posicao": 1,
      "serie": "",
      "uf": "TO"
    },
    {
      "ganhadores": 1,
      "municipio": "PALMAS",
      "nomeFatansiaUL": "",
      "posicao": 2,
      "serie": "",
      "uf": "TO"
    }
  ],
  "listaRateioPremio": [
    {
      "descricaoFaixa": "20 acertos",
      "faixa": 1,
      "numeroDeGanhadores": 2,
      "valorPremio": 2843485.99
    },
    {
      "descricaoFaixa": "19 acertos",
      "faixa": 2,
      "numeroDeGanhadores": 17,
      "valorPremio": 17838.66
    },
    {
      "descricaoFaixa": "18 acertos",
      "faixa": 3,
      "numeroDeGanhadores": 189,
      "valorPremio": 1432.62
    },
    {
      "descricaoFaixa": "17 acertos",
      "faixa": 4,
      "numeroDeGanhadores": 1836,
      "valorPremio": 103.23
    },
    {
      "descricaoFaixa": "16 acertos",
      "faixa": 5,
      "numeroDeGanhadores": 9557,
      "valorPremio": 19.83
    },
    {
      "descricaoFaixa": "15 acertos",
      "faixa": 6,
      "numeroDeGanhadores": 3,
      "valorPremio": 50542.87
    },
    {
      "descricaoFaixa": "0 acertos",
      "faixa": 7,
      "numeroDeGanhadores": 44631,
      "valorPremio": 4.24
    }
  ],
  "listaResultadoEquipeEsportiva": null,
  "localSorteio": "ESPAÇO CAIXA LOTERIAS",
  "nomeMunicipioUFSorteio": "SÃO PAULO, SP",
  "nomeTimeCoracaoMesSorte": "",
  "numero": 1705,
  "numeroConcursoAnterior": 1704,
  "numeroConcursoFinal_0_5": 0,
  "numeroConcursoProximo": 1706,
  "numeroJogo": 16,
  "observacao": "",
  "premiacaoContingencia": null,
  "tipoJogo": "LOTOMANIA",
  "tipoPublicacao": 3,
  "ultimoConcurso": true,
  "valorArrecadado": 6246132.0,
  "valorAcumuladoConcurso_0_5": 0.0,
  "valorAcumuladoConcursoEspecial": 0.0,
  "valorAcumuladoProximoConcurso": 0.0,
  "valorEstimadoProximoConcurso": 400000.0,
  "valorSaldoReservaGarantidora": 0.0,
  "valorTotalPremioFaixaUm": 0.0
}