{
  "acumulado": true,
  "dataApuracao": "04/12/2020",
  "dataProximoConcurso": "08/12/2020",
  "dezenasSorteadasOrdemSorteio": [
    "95",
    "73",
    "13",
    "31",
    "78",
    "03",
    "58",
    "71",
    "04",
    "09",
    "19",
    "74",
    "98",
    "97",
    "30",
    "90",
    "28",
    "36",
    "62",
    "89"
  ],
  "exibirDetalhamentoPorCidade": true,
  "id": null,
  "indicadorConcursoEspecial": 1,
  "listaDezenas": [
    "03",
    "04",
    "09",
    "13",
    "19",
    "28",
    "30",
    "31",
    "36",
    "58",
    "62",
    "71",
    "73",
    "74",
    "78",
    "89",
    "90",
    "95",
    "97",
    "98"
  ],
  "listaDezenasSegundoSorteio": null,
  "listaMunicipioUFGanhadores": [
    {
      "ganhadores": 1,
      "municipio": "SAO JOAO DE MERITI",
      "nomeFatansiaUL": "",
      "posicao": 2,
      "serie": "",
      "uf": "RJ"
    }
  ],
  "listaRateioPremio": [
    {
      "descricaoFaixa": "20 acertos",
      "faixa": 1,
      "numeroDeGanhadores": 0,
      "valorPremio": 0.0
    },
    {
      "descricaoFaixa": "19 acertos",
      "faixa": 2,
      "numeroDeGanhadores": 2,
      "valorPremio": 131436.46
    },
    {
      "descricaoFaixa": "18 acertos",
      "faixa": 3,
      "numeroDeGanhadores": 77,
      "valorPremio": 2133.71
    },
    {
      "descricaoFaixa": "17 acertos",
      "faixa": 4,
      "numeroDeGanhadores": 674,
      "valorPremio": 243.76
    },
    {
      "descricaoFaixa": "16 acertos",
      "faixa": 5,
      "numeroDeGanhadores": 3986,
      "valorPremio": 41.21
    },
    {
      "descricaoFaixa": "15 acertos",
      "faixa": 6,
      "numeroDeGanhadores": 16716,
      "valorPremio": 9.82
    },
    {
      "descricaoFaixa": "0 acertos",
      "faixa": 7,
      "numeroDeGanhadores": 1,
      "valorPremio": 131436.48
    }
  ],
  "listaResultadoEquipeEsportiva": null,
  "localSorteio": "ESPAÇO LOTERIAS CAIXA",
  "nomeMunicipioUFSorteio": "SÃO PAULO, SP",
  "nomeTimeCoracaoMesSorte": "\u0000\u0000\u0000\u0000\u0000\u0000\u0000\u0000\u0000\u0000\u0000\u0000\u0000\u0000\u0000\u0000\u0000",
  "numero": 2132,
  "numeroConcursoAnterior": 2131,
  "numeroConcursoFinal_0_5": 0,
  "numeroConcursoProximo": 2133,
  "numeroJogo": 16,
  "observacao": "ORDEM DE SORTEIO: 95  73  13  31  78  03  58  71  04  09   19  74  98  97  30  90  28  36  62  89",
  "premiacaoContingencia": null,
  "tipoJogo": "LOTOMANIA",
  "tipoPublicacao": 3,
  "ultimoConcurso": true,
  "valorArrecadado": 5414255.0,
  "valorAcumuladoConcurso_0_5": 0.0,
  "valorAcumuladoConcursoEspecial": 2206778.54,
  "valorAcumuladoProximoConcurso": 1460596.44,
  "valorEstimadoProximoConcurso": 2100000.0,
  "valorSaldoReservaGarantidora": 0.0,
  "valorTotalPremioFaixaUm": 0.0
}