{
  "acumulado": false,
  "dataApuracao": "23/01/2008",
  "dataProximoConcurso": "26/01/2008",
  "dezenasSorteadasOrdemSorteio": [
    "95",
    "50",
    "47",
    "49",
    "45",
    "91",
    "18",
    "56",
    "29",
    "04",
    "65",
    "59",
    "70",
    "74",
    "87",
    "72",
    "30",
    "55",
    "52",
    "93"
  ],
  "exibirDetalhamentoPorCidade": true,
  "id": null,
  "indicadorConcursoEspecial": 1,
  "listaDezenas": [
    "04",
    "18",
    "29",
    "30",
    "45",
    "47",
    "49",
    "50",
    "52",
    "55",
    "56",
    "59",
    "65",
    "70",
    "72",
    "74",
    "87",
    "91",
    "93",
    "95"
  ],
  "listaDezenasSegundoSorteio": null,
  "listaMunicipioUFGanhadores": [
    {
      "ganhadores": 1,
      "municipio": "",
      "nomeFatansiaUL": "",
      "posicao": 1,
      "serie": "",
      "uf": "GO"
    }
  ],
  "listaRateioPremio": [
    {
      "descricaoFaixa": "20 acertos",
      "faixa": 1,
      "numeroDeGanhadores": 1,
      "valorPremio": 1990307.19
    },
    {
      "descricaoFaixa": "19 acertos",
      "faixa": 2,
      "numeroDeGanhadores": 13,
      "valorPremio": 22265.74
    },
    {
      "descricaoFaixa": "18 acertos",
      "faixa": 3,
      "numeroDeGanhadores": 210,
      "valorPremio": 1378.35
    },
    {
      "descricaoFaixa": "17 acertos",
      "faixa": 4,
      "numeroDeGanhadores": 1683,
      "valorPremio": 85.99
    },
    {
      "descricaoFaixa": "16 acertos",
      "faixa": 5,
      "numeroDeGanhadores": 9589,
      "valorPremio": 15.1
    },
    {
      "descricaoFaixa": "15 acertos",
      "faixa": 6,
      "numeroDeGanhadores": 0,
      "valorPremio": 0.0
    }
  ],
  "listaResultadoEquipeEsportiva": null,
  "localSorteio": "Caminhão da Sorte",
  "nomeMunicipioUFSorteio": "SÃO JOÃO DA BARRA, RJ",
  "nomeTimeCoracaoMesSorte": "",
  "numero": 795,
  "numeroConcursoAnterior": 794,
  "numeroConcursoFinal_0_5": 0,
  "numeroConcursoProximo": 796,
  "numeroJogo": 16,
  "observacao": "Ganhador de 20 acertos: Itumbiara/GO.\r\nO valor abaixo acumulado é de zero para vinte acertos.",
  "premiacaoContingencia": null,
  "tipoJogo": "LOTOMANIA",
  "tipoPublicacao": 3,
  "ultimoConcurso": true,
  "valorArrecadado": 0.0,
  "valorAcumuladoConcurso_0_5": 0.0,
  "valorAcumuladoConcursoEspecial": 0.0,
  "valorAcumuladoProximoConcurso": 144727.3,
  "valorEstimadoProximoConcurso": 500000.0,
  "valorSaldoReservaGarantidora": 0.0,
  "valorTotalPremioFaixaUm": 0.0
}