{
  "acumulado": false,
  "dataApuracao": "12/05/2014",
  "dataProximoConcurso": "17/05/2014",
  "dezenasSorteadasOrdemSorteio": null,
  "exibirDetalhamentoPorCidade": true,
  "id": null,
  "indicadorConcursoEspecial": 1,
  "listaDezenas": null,
  "listaDezenasSegundoSorteio": null,
  "listaMunicipioUFGanhadores": [
    {
      "ganhadores": 1,
      "municipio": "",
      "nomeFatansiaUL": "",
      "posicao": 1,
      "serie": "",
      "uf": "AC"
    },
    {
      "ganhadores": 1,
      "municipio": "",
      "nomeFatansiaUL": "",
      "posicao": 1,
      "serie": "",
      "uf": "AP"
    },
    {
      "ganhadores": 3,
      "municipio": "",
      "nomeFatansiaUL": "",
      "posicao": 1,
      "serie": "",
      "uf": "BA"
    },
    {
      "ganhadores": 2,
      "municipio": "",
      "nomeFatansiaUL": "",
      "posicao": 1,
      "serie": "",
      "uf": "CE"
    },
    {
      "ganhadores": 1,
      "municipio": "",
      "nomeFatansiaUL": "",
      "posicao": 1,
      "serie": "",
      "uf": "DF"
    },
    {
      "ganhadores": 2,
      "municipio": "",
      "nomeFatansiaUL": "",
      "posicao": 1,
      "serie": "",
      "uf": "ES"
    },
    {
      "ganhadores": 1,
      "municipio": "",
      "nomeFatansiaUL": "",
      "posicao": 1,
      "serie": "",
      "uf": "GO"
    },
    {
      "ganhadores": 1,
      "municipio": "",
      "nomeFatansiaUL": "",
      "posicao": 1,
      "serie": "",
      "uf": "MA"
    },
    {
      "ganhadores": 10,
      "municipio": "",
      "nomeFatansiaUL": "",
      "posicao": 1,
      "serie": "",
      "uf": "MG"
    },
    {
      "ganhadores": 1,
      "municipio": "",
      "nomeFatansiaUL": "",
      "posicao": 1,
      "serie": "",
      "uf": "MS"
    },
    {
      "ganhadores": 2,
      "municipio": "",
      "nomeFatansiaUL": "",
      "posicao": 1,
      "serie": "",
      "uf": "MT"
    },
    {
      "ganhadores": 1,
      "municipio": "",
      "nomeFatansiaUL": "",
      "posicao": 1,
      "serie": "",
      "uf": "PA"
    },
    {
      "ganhadores": 1,
      "municipio": "",
      "nomeFatansiaUL": "",
      "posicao": 1,
      "serie": "",
      "uf": "PB"
    },
    {
      "ganhadores": 3,
      "municipio": "",
      "nomeFatansiaUL": "",
      "posicao": 1,
      "serie": "",
      "uf": "PE"
    },
    {
      "ganhadores": 3,
      "municipio": "",
      "nomeFatansiaUL": "",
      "posicao": 1,
      "serie": "",
      "uf": "PR"
    },
    {
      "ganhadores": 8,
      "municipio": "",
      "nomeFatansiaUL": "",
      "posicao": 1,
      "serie": "",
      "uf": "RJ"
    },
    {
      "ganhadores": 1,
      "municipio": "",
      "nomeFatansiaUL": "",
      "posicao": 1,
      "serie": "",
      "uf": "RO"
    },
    {
      "ganhadores": 2,
      "municipio": "",
      "nomeFatansiaUL": "",
      "posicao": 1,
      "serie": "",
      "uf": "RS"
    },
    {
      "ganhadores": 5,
      "municipio": "",
      "nomeFatansiaUL": "",
      "posicao": 1,
      "serie": "",
      "uf": "SC"
    },
    {
      "ganhadores": 2,
      "municipio": "",
      "nomeFatansiaUL": "",
      "posicao": 1,
      "serie": "",
      "uf": "SE"
    },
    {
      "ganhadores": 23,
      "municipio": "",
      "nomeFatansiaUL": "",
      "posicao": 1,
      "serie": "",
      "uf": "SP"
    },
    {
      "ganhadores": 2,
      "municipio": "",
      "nomeFatansiaUL": "",
      "posicao": 1,
      "serie": "",
      "uf": "TO"
    }
  ],
  "listaRateioPremio": [
    {
      "descricaoFaixa": "1º (14 acertos)",
      "faixa": 1,
      "numeroDeGanhadores": 76,
      "valorPremio": 15032.78
    },
    {
      "descricaoFaixa": "2º (13 acertos)",
      "faixa": 2,
      "numeroDeGanhadores": 1844,
      "valorPremio": 77.4
    }
  ],
  "listaResultadoEquipeEsportiva": [
    {
      "diaSemana": "Domingo",
      "dtJogo": "11/05/2014",
      "icSorteioResultado": 0,
      "nomeCampeonato": "",
      "nomeEquipeDois": "FLAMENGO",
      "nomeEquipeUm": "FLUMINENSE",
      "nuConcurso": 606,
      "nuGolEquipeDois": 0,
      "nuGolEquipeUm": 2,
      "nuJogo": 19,
      "nuSequencial": 1,
      "resultado": null,
      "siglaPaisDois": "",
      "siglaPaisUm": "",
      "siglaUFDois": "RJ",
      "siglaUFUm": "RJ"
    },
    {
      "diaSemana": "Domingo",
      "dtJogo": "11/05/2014",
      "icSorteioResultado": 0,
      "nomeCampeonato": "",
      "nomeEquipeDois": "CORINTHIANS",
      "nomeEquipeUm": "SAO PAULO",
      "nuConcurso": 606,
      "nuGolEquipeDois": 1,
      "nuGolEquipeUm": 1,
      "nuJogo": 19,
      "nuSequencial": 2,
      "resultado": null,
      "siglaPaisDois": "",
      "siglaPaisUm": "",
      "siglaUFDois": "SP",
      "siglaUFUm": "SP"
    },
    {
      "diaSemana": "Domingo",
      "dtJogo": "11/05/2014",
      "icSorteioResultado": 0,
      "nomeCampeonato": "",
      "nomeEquipeDois": "VITORIA",
      "nomeEquipeUm": "BAHIA",
      "nuConcurso": 606,
      "nuGolEquipeDois": 1,
      "nuGolEquipeUm": 1,
      "nuJogo": 19,
      "nuSequencial": 3,
      "resultado": null,
      "siglaPaisDois": "",
      "siglaPaisUm": "",
      "siglaUFDois": "BA",
      "siglaUFUm": "BA"
    },
    {
      "diaSemana": "Sábado",
      "dtJogo": "10/05/2014",
      "icSorteioResultado": 0,
      "nomeCampeonato": "",
      "nomeEquipeDois": "ABC",
      "nomeEquipeUm": "PONTE PRETA",
      "nuConcurso": 606,
      "nuGolEquipeDois": 1,
      "nuGolEquipeUm": 2,
      "nuJogo": 19,
      "nuSequencial": 4,
      "resultado": null,
      "siglaPaisDois": "",
      "siglaPaisUm": "",
      "siglaUFDois": "RN",
      "siglaUFUm": "SP"
    },
    {
      "diaSemana": "",
      "dtJogo": "",
      "icSorteioResultado": 1,
      "nomeCampeonato": "",
      "nomeEquipeDois": "AVAI",
      "nomeEquipeUm": "SAMPAIO CORREA",
      "nuConcurso": 606,
      "nuGolEquipeDois": 1,
      "nuGolEquipeUm": 0,
      "nuJogo": 19,
      "nuSequencial": 5,
      "resultado": null,
      "siglaPaisDois": "",
      "siglaPaisUm": "",
      "siglaUFDois": "SC",
      "siglaUFUm": "MA"
    },
    {
      "diaSemana": "Sábado",
      "dtJogo": "10/05/2014",
      "icSorteioResultado": 0,
      "nomeCampeonato": "",
      "nomeEquipeDois": "NAUTICO",
      "nomeEquipeUm": "JOINVILLE",
      "nuConcurso": 606,
      "nuGolEquipeDois": 0,
      "nuGolEquipeUm": 1,
      "nuJogo": 19,
      "nuSequencial": 6,
      "resultado": null,
      "siglaPaisDois": "",
      "siglaPaisUm": "",
      "siglaUFDois": "PE",
      "siglaUFUm": "SC"
    },
    {
      "diaSemana": "Sábado",
      "dtJogo": "10/05/2014",
      "icSorteioResultado": 0,
      "nomeCampeonato": "",
      "nomeEquipeDois": "PARANA",
      "nomeEquipeUm": "CEARA",
      "nuConcurso": 606,
      "nuGolEquipeDois": 1,
      "nuGolEquipeUm": 2,
      "nuJogo": 19,
      "nuSequencial": 7,
      "resultado": null,
      "siglaPaisDois": "",
      "siglaPaisUm": "",
      "siglaUFDois": "PR",
      "siglaUFUm": "CE"
    },
    {
      "diaSemana": "Sábado",
      "dtJogo": "10/05/2014",
      "icSorteioResultado": 0,
      "nomeCampeonato": "",
      "nomeEquipeDois": "ATHLETICO",
      "nomeEquipeUm": "INTERNACIONAL",
      "nuConcurso": 606,
      "nuGolEquipeDois": 1,
      "nuGolEquipeUm": 2,
      "nuJogo": 19,
      "nuSequencial": 8,
      "resultado": null,
      "siglaPaisDois": "",
      "siglaPaisUm": "",
      "siglaUFDois": "PR",
      "siglaUFUm": "RS"
    },
    {
      "diaSemana": "Sábado",
      "dtJogo": "10/05/2014",
      "icSorteioResultado": 0,
      "nomeCampeonato": "",
      "nomeEquipeDois": "GOIAS",
      "nomeEquipeUm": "PALMEIRAS",
      "nuConcurso": 606,
      "nuGolEquipeDois": 0,
      "nuGolEquipeUm": 2,
      "nuJogo": 19,
      "nuSequencial": 9,
      "resultado": null,
      "siglaPaisDois": "",
      "siglaPaisUm": "",
      "siglaUFDois": "GO",
      "siglaUFUm": "SP"
    },
    {
      "diaSemana": "Sábado",
      "dtJogo": "10/05/2014",
      "icSorteioResultado": 0,
      "nomeCampeonato": "",
      "nomeEquipeDois": "CRICIUMA",
      "nomeEquipeUm": "BOTAFOGO",
      "nuConcurso": 606,
      "nuGolEquipeDois": 0,
      "nuGolEquipeUm": 6,
      "nuJogo": 19,
      "nuSequencial": 10,
      "resultado": null,
      "siglaPaisDois": "",
      "siglaPaisUm": "",
      "siglaUFDois": "SC",
      "siglaUFUm": "RJ"
    },
    {
      "diaSemana": "Domingo",
      "dtJogo": "11/05/2014",
      "icSorteioResultado": 0,
      "nomeCampeonato": "",
      "nomeEquipeDois": "SPORT",
      "nomeEquipeUm": "CORITIBA",
      "nuConcurso": 606,
      "nuGolEquipeDois": 1,
      "nuGolEquipeUm": 0,
      "nuJogo": 19,
      "nuSequencial": 11,
      "resultado": null,
      "siglaPaisDois": "",
      "siglaPaisUm": "",
      "siglaUFDois": "PE",
      "siglaUFUm": "PR"
    },
    {
      "diaSemana": "Domingo",
      "dtJogo": "11/05/2014",
      "icSorteioResultado": 0,
      "nomeCampeonato": "",
      "nomeEquipeDois": "SANTOS",
      "nomeEquipeUm": "FIGUEIRENSE",
      "nuConcurso": 606,
      "nuGolEquipeDois": 2,
      "nuGolEquipeUm": 0,
      "nuJogo": 19,
      "nuSequencial": 12,
      "resultado": null,
      "siglaPaisDois": "",
      "siglaPaisUm": "",
      "siglaUFDois": "SP",
      "siglaUFUm": "SC"
    },
    {
      "diaSemana": "Domingo",
      "dtJogo": "11/05/2014",
      "icSorteioResultado": 0,
      "nomeCampeonato": "",
      "nomeEquipeDois": "GREMIO",
      "nomeEquipeUm": "CHAPECOENSE",
      "nuConcurso": 606,
      "nuGolEquipeDois": 2,
      "nuGolEquipeUm": 1,
      "nuJogo": 19,
      "nuSequencial": 13,
      "resultado": null,
      "siglaPaisDois": "",
      "siglaPaisUm": "",
      "siglaUFDois": "RS",
      "siglaUFUm": "SC"
    },
    {
      "diaSemana": "Domingo",
      "dtJogo": "11/05/2014",
      "icSorteioResultado": 0,
      "nomeCampeonato": "",
      "nomeEquipeDois": "CRUZEIRO",
      "nomeEquipeUm": "ATLETICO",
      "nuConcurso": 606,
      "nuGolEquipeDois": 1,
      "nuGolEquipeUm": 2,
      "nuJogo": 19,
      "nuSequencial": 14,
      "resultado": null,
      "siglaPaisDois": "",
      "siglaPaisUm": "",
      "siglaUFDois": "MG",
      "siglaUFUm": "MG"
    }
  ],
  "localSorteio": "",
  "nomeMunicipioUFSorteio": "",
  "nomeTimeCoracaoMesSorte": "",
  "numero": 606,
  "numeroConcursoAnterior": 605,
  "numeroConcursoFinal_0_5": 610,
  "numeroConcursoProximo": 607,
  "numeroJogo": 19,
  "observacao": "Tendo em vista o adiamento da realização da partida (SPORT CLUBE DO RECIFE (SPORT/PE) x ESPORTE CLUBE BAHIA S/A (BAHIA/BA) e Jogo 7 (CLUBE NÁUTICO CAPIBARIBE (NÁUTICO/PE) x CLUB DE REGATAS VASCO DA GAMA (VASCO DA GAMA/RJ),dos concursos 607 da Loteca e 609 da Lotogol, seus resultados serão obtidos por meio de sorteio, em conformidade ao regramento destas modalidades. Desta forma, os sorteios serão realizados no dia 19/05/2014, às 15h, no Auditório da CAIXA em Brasília, mantido o horário normal de apuração, às 18h.",
  "premiacaoContingencia": null,
  "tipoJogo": "LOTECA",
  "tipoPublicacao": 3,
  "ultimoConcurso": true,
  "valorArrecadado": 2485917.5,
  "valorAcumuladoConcurso_0_5": 177891.87,
  "valorAcumuladoConcursoEspecial": 0.0,
  "valorAcumuladoProximoConcurso": 0.0,
  "valorEstimadoProximoConcurso": 300000.0,
  "valorSaldoReservaGarantidora": 0.0,
  "valorTotalPremioFaixaUm": 0.0
}