{
  "acumulado": false,
  "dataApuracao": "01/04/2002",
  "dataProximoConcurso": "06/04/2002",
  "dezenasSorteadasOrdemSorteio": null,
  "exibirDetalhamentoPorCidade": true,
  "id": null,
  "indicadorConcursoEspecial": 1,
  "listaDezenas": null,
  "listaDezenasSegundoSorteio": null,
  "listaMunicipioUFGanhadores": [
    {
      "ganhadores": 1,
      "municipio": "",
      "nomeFatansiaUL": "",
      "posicao": 1,
      "serie": "",
      "uf": "GO"
    },
    {
      "ganhadores": 1,
      "municipio": "",
      "nomeFatansiaUL": "",
      "posicao": 1,
      "serie": "",
      "uf": "MG"
    }
  ],
  "listaRateioPremio": [
    {
      "descricaoFaixa": "1º (14 acertos)",
      "faixa": 1,
      "numeroDeGanhadores": 2,
      "valorPremio": 53954.84
    },
    {
      "descricaoFaixa": "2º (13 acertos)",
      "faixa": 2,
      "numeroDeGanhadores": 126,
      "valorPremio": 856.42
    },
    {
      "descricaoFaixa": "3 acertos",
      "faixa": 3,
      "numeroDeGanhadores": 2354,
      "valorPremio": 60.89
    }
  ],
  "listaResultadoEquipeEsportiva": [
    {
      "diaSemana": "Domingo",
      "dtJogo": "31/03/2002",
      "icSorteioResultado": 0,
      "nomeCampeonato": "",
      "nomeEquipeDois": "SAO PAULO",
      "nomeEquipeUm": "CORINTHIANS",
      "nuConcurso": 7,
      "nuGolEquipeDois": 1,
      "nuGolEquipeUm": 3,
      "nuJogo": 19,
      "nuSequencial": 1,
      "resultado": null,
      "siglaPaisDois": "",
      "siglaPaisUm": "",
      "siglaUFDois": "SP",
      "siglaUFUm": "SP"
    },
    {
      "diaSemana": "Sábado",
      "dtJogo": "30/03/2002",
      "icSorteioResultado": 0,
      "nomeCampeonato": "",
      "nomeEquipeDois": "GUARANI",
      "nomeEquipeUm": "PALMEIRAS",
      "nuConcurso": 7,
      "nuGolEquipeDois": 2,
      "nuGolEquipeUm": 3,
      "nuJogo": 19,
      "nuSequencial": 2,
      "resultado": null,
      "siglaPaisDois": "",
      "siglaPaisUm": "",
      "siglaUFDois": "SP",
      "siglaUFUm": "SP"
    },
    {
      "diaSemana": "Sábado",
      "dtJogo": "30/03/2002",
      "icSorteioResultado": 0,
      "nomeCampeonato": "",
      "nomeEquipeDois": "NAUTICO",
      "nomeEquipeUm": "SANTA CRUZ",
      "nuConcurso": 7,
      "nuGolEquipeDois": 1,
      "nuGolEquipeUm": 1,
      "nuJogo": 19,
      "nuSequencial": 3,
      "resultado": null,
      "siglaPaisDois": "",
      "siglaPaisUm": "",
      "siglaUFDois": "PE",
      "siglaUFUm": "PE"
    },
    {
      "diaSemana": "Domingo",
      "dtJogo": "31/03/2002",
      "icSorteioResultado": 0,
      "nomeCampeonato": "",
      "nomeEquipeDois": "AMERICA",
      "nomeEquipeUm": "BOTAFOGO",
      "nuConcurso": 7,
      "nuGolEquipeDois": 1,
      "nuGolEquipeUm": 0,
      "nuJogo": 19,
      "nuSequencial": 4,
      "resultado": null,
      "siglaPaisDois": "",
      "siglaPaisUm": "",
      "siglaUFDois": "RJ",
      "siglaUFUm": "RJ"
    },
    {
      "diaSemana": "Sábado",
      "dtJogo": "30/03/2002",
      "icSorteioResultado": 0,
      "nomeCampeonato": "",
      "nomeEquipeDois": "SANTOS",
      "nomeEquipeUm": "VASCO DA GAMA",
      "nuConcurso": 7,
      "nuGolEquipeDois": 1,
      "nuGolEquipeUm": 1,
      "nuJogo": 19,
      "nuSequencial": 5,
      "resultado": null,
      "siglaPaisDois": "",
      "siglaPaisUm": "",
      "siglaUFDois": "SP",
      "siglaUFUm": "RJ"
    },
    {
      "diaSemana": "Domingo",
      "dtJogo": "31/03/2002",
      "icSorteioResultado": 0,
      "nomeCampeonato": "",
      "nomeEquipeDois": "SAO  CAETANO",
      "nomeEquipeUm": "FLAMENGO",
      "nuConcurso": 7,
      "nuGolEquipeDois": 2,
      "nuGolEquipeUm": 1,
      "nuJogo": 19,
      "nuSequencial": 6,
      "resultado": null,
      "siglaPaisDois": "",
      "siglaPaisUm": "",
      "siglaUFDois": "SP",
      "siglaUFUm": "RJ"
    },
    {
      "diaSemana": "Sábado",
      "dtJogo": "30/03/2002",
      "icSorteioResultado": 0,
      "nomeCampeonato": "",
      "nomeEquipeDois": "AMERICANO",
      "nomeEquipeUm": "FLUMINENSE",
      "nuConcurso": 7,
      "nuGolEquipeDois": 0,
      "nuGolEquipeUm": 2,
      "nuJogo": 19,
      "nuSequencial": 7,
      "resultado": null,
      "siglaPaisDois": "",
      "siglaPaisUm": "",
      "siglaUFDois": "RJ",
      "siglaUFUm": "RJ"
    },
    {
      "diaSemana": "Sábado",
      "dtJogo": "30/03/2002",
      "icSorteioResultado": 0,
      "nomeCampeonato": "",
      "nomeEquipeDois": "PONTE PRETA",
      "nomeEquipeUm": "BANGU",
      "nuConcurso": 7,
      "nuGolEquipeDois": 1,
      "nuGolEquipeUm": 1,
      "nuJogo": 19,
      "nuSequencial": 8,
      "resultado": null,
      "siglaPaisDois": "",
      "siglaPaisUm": "",
      "siglaUFDois": "SP",
      "siglaUFUm": "RJ"
    },
    {
      "diaSemana": "Domingo",
      "dtJogo": "31/03/2002",
      "icSorteioResultado": 0,
      "nomeCampeonato": "",
      "nomeEquipeDois": "FORTALEZA",
      "nomeEquipeUm": "BAHIA",
      "nuConcurso": 7,
      "nuGolEquipeDois": 2,
      "nuGolEquipeUm": 3,
      "nuJogo": 19,
      "nuSequencial": 9,
      "resultado": null,
      "siglaPaisDois": "",
      "siglaPaisUm": "",
      "siglaUFDois": "CE",
      "siglaUFUm": "BA"
    },
    {
      "diaSemana": "Domingo",
      "dtJogo": "31/03/2002",
      "icSorteioResultado": 0,
      "nomeCampeonato": "",
      "nomeEquipeDois": "CRB",
      "nomeEquipeUm": "BOTAFOGO",
      "nuConcurso": 7,
      "nuGolEquipeDois": 4,
      "nuGolEquipeUm": 1,
      "nuJogo": 19,
      "nuSequencial": 10,
      "resultado": null,
      "siglaPaisDois": "",
      "siglaPaisUm": "",
      "siglaUFDois": "AL",
      "siglaUFUm": "PB"
    },
    {
      "diaSemana": "Domingo",
      "dtJogo": "31/03/2002",
      "icSorteioResultado": 0,
      "nomeCampeonato": "",
      "nomeEquipeDois": "GOIAS",
      "nomeEquipeUm": "GAMA",
      "nuConcurso": 7,
      "nuGolEquipeDois": 0,
      "nuGolEquipeUm": 4,
      "nuJogo": 19,
      "nuSequencial": 11,
      "resultado": null,
      "siglaPaisDois": "",
      "siglaPaisUm": "",
      "siglaUFDois": "GO",
      "siglaUFUm": "DF"
    },
    {
      "diaSemana": "Domingo",
      "dtJogo": "31/03/2002",
      "icSorteioResultado": 0,
      "nomeCampeonato": "",
      "nomeEquipeDois": "CRUZEIRO",
      "nomeEquipeUm": "PELOTAS",
      "nuConcurso": 7,
      "nuGolEquipeDois": 3,
      "nuGolEquipeUm": 2,
      "nuJogo": 19,
      "nuSequencial": 12,
      "resultado": null,
      "siglaPaisDois": "",
      "siglaPaisUm": "",
      "siglaUFDois": "MG",
      "siglaUFUm": "RS"
    },
    {
      "diaSemana": "Domingo",
      "dtJogo": "31/03/2002",
      "icSorteioResultado": 0,
      "nomeCampeonato": "",
      "nomeEquipeDois": "CORITIBA",
      "nomeEquipeUm": "GREMIO",
      "nuConcurso": 7,
      "nuGolEquipeDois": 3,
      "nuGolEquipeUm": 4,
      "nuJogo": 19,
      "nuSequencial": 13,
      "resultado": null,
      "siglaPaisDois": "",
      "siglaPaisUm": "",
      "siglaUFDois": "PR",
      "siglaUFUm": "RS"
    },
    {
      "diaSemana": "Domingo",
      "dtJogo": "31/03/2002",
      "icSorteioResultado": 0,
      "nomeCampeonato": "",
      "nomeEquipeDois": "INTERNACIONAL",
      "nomeEquipeUm": "ATLETICO",
      "nuConcurso": 7,
      "nuGolEquipeDois": 1,
      "nuGolEquipeUm": 3,
      "nuJogo": 19,
      "nuSequencial": 14,
      "resultado": null,
      "siglaPaisDois": "",
      "siglaPaisUm": "",
      "siglaUFDois": "RS",
      "siglaUFUm": "MG"
    }
  ],
  "localSorteio": "",
  "nomeMunicipioUFSorteio": "",
  "nomeTimeCoracaoMesSorte": "",
  "numero": 7,
  "numeroConcursoAnterior": 6,
  "numeroConcursoFinal_0_5": 10,
  "numeroConcursoProximo": 8,
  "numeroJogo": 19,
  "observacao": "MARQUE UM GOLAÇO VOCE TAMBEM. APOSTE NA LOTECA E NA LOTOGOL. ESTIMATIVA DE PRÊMIO PRÓXIMO CONCURSO(14 ACERTOS): R$120.000,00.",
  "premiacaoContingencia": null,
  "tipoJogo": "LOTECA",
  "tipoPublicacao": 3,
  "ultimoConcurso": true,
  "valorArrecadado": 0.0,
  "valorAcumuladoConcurso_0_5": 0.0,
  "valorAcumuladoConcursoEspecial": 0.0,
  "valorAcumuladoProximoConcurso": 0.0,
  "valorEstimadoProximoConcurso": 0.0,
  "valorSaldoReservaGarantidora": 0.0,
  "valorTotalPremioFaixaUm": 0.0
}