{
  "acumulado": true,
  "dataApuracao": "23/01/2010",
  "dataProximoConcurso": "30/01/2010",
  "dezenasSorteadasOrdemSorteio": [
    "12",
    "52",
    "63",
    "60",
    "28",
    "66",
    "05"
  ],
  "exibirDetalhamentoPorCidade": true,
  "id": null,
  "indicadorConcursoEspecial": 1,
  "listaDezenas": [
    "05",
    "12",
    "28",
    "52",
    "60",
    "63",
    "66"
  ],
  "listaDezenasSegundoSorteio": null,
  "listaMunicipioUFGanhadores": [],
  "listaRateioPremio": [
    {
      "descricaoFaixa": "7 acertos",
      "faixa": 1,
      "numeroDeGanhadores": 0,
      "valorPremio": 0.0
    },
    {
      "descricaoFaixa": "6 acertos",
      "faixa": 2,
      "numeroDeGanhadores": 3,
      "valorPremio": 33373.73
    },
    {
      "descricaoFaixa": "5 acertos",
      "faixa": 3,
      "numeroDeGanhadores": 97,
      "valorPremio": 983.02
    },
    {
      "descricaoFaixa": "4 acertos",
      "faixa": 4,
      "numeroDeGanhadores": 2228,
      "valorPremio": 6.0
    },
    {
      "descricaoFaixa": "3 acertos",
      "faixa": 5,
      "numeroDeGanhadores": 20943,
      "valorPremio": 2.0
    },
    {
      "descricaoFaixa": "Time do Coração",
      "faixa": 6,
      "numeroDeGanhadores": 5225,
      "valorPremio": 2.0
    }
  ],
  "listaResultadoEquipeEsportiva": null,
  "localSorteio": "Caminhão da Sorte",
  "nomeMunicipioUFSorteio": "MACEIÓ, AL",
  "nomeTimeCoracaoMesSorte": "LONDRINA/PR",
  "numero": 99,
  "numeroConcursoAnterior": 98,
  "numeroConcursoFinal_0_5": 100,
  "numeroConcursoProximo": 100,
  "numeroJogo": 20,
  "observacao": "",
  "premiacaoContingencia": null,
  "tipoJogo": "TIMEMANIA",
  "tipoPublicacao": 3,
  "ultimoConcurso": true,
  "valorArrecadado": 1179286.0,
  "valorAcumuladoConcurso_0_5": 439140.55,
  "valorAcumuladoConcursoEspecial": 0.0,
  "valorAcumuladoProximoConcurso": 439140.55,
  "valorEstimadoProximoConcurso": 600000.0,
  "valorSaldoReservaGarantidora": 0.0,
  "valorTotalPremioFaixaUm": 0.0
}